{"nm":"loading place","ddd":0,"h":160,"w":320,"meta":{"g":"@lottiefiles/toolkit-js 0.33.2"},"layers":[{"ty":4,"nm":"cielo/loading place contornos","sr":1,"st":0,"op":110,"ip":0,"hd":false,"ddd":0,"bm":0,"hasMask":false,"ao":0,"ks":{"a":{"a":0,"k":[160,80,0],"ix":1},"s":{"a":0,"k":[100,100,100],"ix":6},"sk":{"a":0,"k":0},"p":{"a":0,"k":[160,80,0],"ix":2},"r":{"a":0,"k":0,"ix":10},"sa":{"a":0,"k":0},"o":{"a":0,"k":100,"ix":11}},"ef":[],"shapes":[{"ty":"gr","bm":0,"hd":false,"mn":"ADBE Vector Group","nm":"Grupo 1","ix":1,"cix":2,"np":2,"it":[{"ty":"sh","bm":0,"hd":false,"mn":"ADBE Vector Shape - Group","nm":"Trazado 1","ix":1,"d":1,"ks":{"a":0,"k":{"c":true,"i":[[1.733,0],[0,0],[0,1.733],[-1.734,0],[0,0],[0,-1.734]],"o":[[0,0],[-1.734,0],[0,-1.734],[0,0],[1.733,0],[0,1.733]],"v":[[10.212,3.139],[-10.212,3.139],[-13.351,0.001],[-10.212,-3.139],[10.212,-3.139],[13.351,0.001]]},"ix":2}},{"ty":"fl","bm":0,"hd":false,"mn":"ADBE Vector Graphic - Fill","nm":"Relleno 1","c":{"a":0,"k":[0.8275,0.1843,0.1843],"ix":4},"r":1,"o":{"a":0,"k":100,"ix":5}},{"ty":"tr","a":{"a":0,"k":[0,0],"ix":1},"s":{"a":0,"k":[100,100],"ix":3},"sk":{"a":0,"k":0,"ix":4},"p":{"a":0,"k":[101.588,29.28],"ix":2},"r":{"a":0,"k":0,"ix":6},"sa":{"a":0,"k":0,"ix":5},"o":{"a":0,"k":100,"ix":7}}]},{"ty":"gr","bm":0,"hd":false,"mn":"ADBE Vector Group","nm":"Grupo 2","ix":2,"cix":2,"np":2,"it":[{"ty":"sh","bm":0,"hd":false,"mn":"ADBE Vector Shape - Group","nm":"Trazado 1","ix":1,"d":1,"ks":{"a":0,"k":{"c":true,"i":[[1.734,0],[0,0],[0,1.734],[-1.734,0],[0,0],[0,-1.733]],"o":[[0,0],[-1.734,0],[0,-1.733],[0,0],[1.734,0],[0,1.734]],"v":[[7.487,3.139],[-7.487,3.139],[-10.626,-0.001],[-7.487,-3.139],[7.487,-3.139],[10.626,-0.001]]},"ix":2}},{"ty":"fl","bm":0,"hd":false,"mn":"ADBE Vector Graphic - Fill","nm":"Relleno 1","c":{"a":0,"k":[0.8275,0.1843,0.1843],"ix":4},"r":1,"o":{"a":0,"k":100,"ix":5}},{"ty":"tr","a":{"a":0,"k":[0,0],"ix":1},"s":{"a":0,"k":[100,100],"ix":3},"sk":{"a":0,"k":0,"ix":4},"p":{"a":0,"k":[95.031,26.141],"ix":2},"r":{"a":0,"k":0,"ix":6},"sa":{"a":0,"k":0,"ix":5},"o":{"a":0,"k":100,"ix":7}}]},{"ty":"gr","bm":0,"hd":false,"mn":"ADBE Vector Group","nm":"Grupo 3","ix":3,"cix":2,"np":2,"it":[{"ty":"sh","bm":0,"hd":false,"mn":"ADBE Vector Shape - Group","nm":"Trazado 1","ix":1,"d":1,"ks":{"a":0,"k":{"c":true,"i":[[2.601,0],[0,0],[0,2.601],[-2.601,0],[0,0],[0,-2.601]],"o":[[0,0],[-2.601,0],[0,-2.601],[0,0],[2.601,0],[0,2.601]],"v":[[13.833,4.709],[-13.833,4.709],[-18.542,0],[-13.833,-4.709],[13.833,-4.709],[18.541,0]]},"ix":2}},{"ty":"fl","bm":0,"hd":false,"mn":"ADBE Vector Graphic - Fill","nm":"Relleno 1","c":{"a":0,"k":[0.8275,0.1843,0.1843],"ix":4},"r":1,"o":{"a":0,"k":100,"ix":5}},{"ty":"tr","a":{"a":0,"k":[0,0],"ix":1},"s":{"a":0,"k":[100,100],"ix":3},"sk":{"a":0,"k":0,"ix":4},"p":{"a":0,"k":[223.401,42.837],"ix":2},"r":{"a":0,"k":0,"ix":6},"sa":{"a":0,"k":0,"ix":5},"o":{"a":0,"k":100,"ix":7}}]},{"ty":"gr","bm":0,"hd":false,"mn":"ADBE Vector Group","nm":"Grupo 4","ix":4,"cix":2,"np":2,"it":[{"ty":"sh","bm":0,"hd":false,"mn":"ADBE Vector Shape - Group","nm":"Trazado 1","ix":1,"d":1,"ks":{"a":0,"k":{"c":true,"i":[[2.601,0],[0,0],[0,2.601],[-2.601,0],[0,0],[0,-2.601]],"o":[[0,0],[-2.601,0],[0,-2.601],[0,0],[2.601,0],[0,2.601]],"v":[[11.231,4.708],[-11.23,4.708],[-15.939,-0.001],[-11.23,-4.708],[11.231,-4.708],[15.939,-0.001]]},"ix":2}},{"ty":"fl","bm":0,"hd":false,"mn":"ADBE Vector Graphic - Fill","nm":"Relleno 1","c":{"a":0,"k":[0.8275,0.1843,0.1843],"ix":4},"r":1,"o":{"a":0,"k":100,"ix":5}},{"ty":"tr","a":{"a":0,"k":[0,0],"ix":1},"s":{"a":0,"k":[100,100],"ix":3},"sk":{"a":0,"k":0,"ix":4},"p":{"a":0,"k":[226.003,38.128],"ix":2},"r":{"a":0,"k":0,"ix":6},"sa":{"a":0,"k":0,"ix":5},"o":{"a":0,"k":100,"ix":7}}]}],"ind":1},{"ty":4,"nm":"casita/loading place contornos","sr":1,"st":0,"op":104,"ip":0,"hd":false,"ddd":0,"bm":0,"hasMask":false,"ao":0,"ks":{"a":{"a":0,"k":[160,137,0],"ix":1},"s":{"a":1,"k":[{"o":{"x":0.333,"y":0},"i":{"x":0.667,"y":1},"s":[100,100,100],"t":0},{"o":{"x":0.333,"y":0},"i":{"x":0.667,"y":1},"s":[110,90,100],"t":8},{"o":{"x":0.333,"y":0},"i":{"x":0.667,"y":1},"s":[100,100,100],"t":16},{"o":{"x":0.333,"y":0},"i":{"x":0.667,"y":1},"s":[100,100,100],"t":33},{"o":{"x":0.333,"y":0},"i":{"x":0.667,"y":1},"s":[110,90,100],"t":41},{"o":{"x":0.333,"y":0},"i":{"x":0.667,"y":1},"s":[100,100,100],"t":49},{"o":{"x":0.333,"y":0},"i":{"x":0.667,"y":1},"s":[100,100,100],"t":66},{"o":{"x":0.333,"y":0},"i":{"x":0.667,"y":1},"s":[110,90,100],"t":74},{"s":[100,100,100],"t":82}],"ix":6},"sk":{"a":0,"k":0},"p":{"a":0,"k":[160,137,0],"ix":2},"r":{"a":0,"k":0,"ix":10},"sa":{"a":0,"k":0},"o":{"a":0,"k":100,"ix":11}},"ef":[],"shapes":[{"ty":"gr","bm":0,"hd":false,"mn":"ADBE Vector Group","nm":"Grupo 1","ix":1,"cix":2,"np":3,"it":[{"ty":"sh","bm":0,"hd":false,"mn":"ADBE Vector Shape - Group","nm":"Trazado 1","ix":1,"d":1,"ks":{"a":0,"k":{"c":true,"i":[[0,-0.704],[0.704,0],[0,0.703],[-0.704,0]],"o":[[0,0.703],[-0.704,0],[0,-0.704],[0.704,0]],"v":[[1.275,0.001],[-0.001,1.275],[-1.275,0.001],[-0.001,-1.275]]},"ix":2}},{"ty":"st","bm":0,"hd":false,"mn":"ADBE Vector Graphic - Stroke","nm":"Trazo 1","lc":2,"lj":1,"ml":10,"o":{"a":0,"k":100,"ix":4},"w":{"a":0,"k":1.5,"ix":5},"c":{"a":0,"k":[0.1098,0.1569,0.2],"ix":3}},{"ty":"fl","bm":0,"hd":false,"mn":"ADBE Vector Graphic - Fill","nm":"Relleno 1","c":{"a":0,"k":[1,1,1],"ix":4},"r":1,"o":{"a":0,"k":100,"ix":5}},{"ty":"tr","a":{"a":0,"k":[0,0],"ix":1},"s":{"a":0,"k":[100,100],"ix":3},"sk":{"a":0,"k":0,"ix":4},"p":{"a":0,"k":[140.402,122.279],"ix":2},"r":{"a":0,"k":0,"ix":6},"sa":{"a":0,"k":0,"ix":5},"o":{"a":0,"k":100,"ix":7}}]},{"ty":"gr","bm":0,"hd":false,"mn":"ADBE Vector Group","nm":"Grupo 2","ix":2,"cix":2,"np":3,"it":[{"ty":"sh","bm":0,"hd":false,"mn":"ADBE Vector Shape - Group","nm":"Trazado 1","ix":1,"d":1,"ks":{"a":0,"k":{"c":false,"i":[[0,0],[0,0]],"o":[[0,0],[0,0]],"v":[[-3.124,3.124],[3.124,-3.124]]},"ix":2}},{"ty":"st","bm":0,"hd":false,"mn":"ADBE Vector Graphic - Stroke","nm":"Trazo 1","lc":2,"lj":1,"ml":10,"o":{"a":0,"k":100,"ix":4},"w":{"a":0,"k":1.5,"ix":5},"c":{"a":0,"k":[0.8275,0.1843,0.1843],"ix":3}},{"ty":"fl","bm":0,"hd":false,"mn":"ADBE Vector Graphic - Fill","nm":"Relleno 1","c":{"a":0,"k":[1,1,1],"ix":4},"r":1,"o":{"a":0,"k":100,"ix":5}},{"ty":"tr","a":{"a":0,"k":[0,0],"ix":1},"s":{"a":0,"k":[100,100],"ix":3},"sk":{"a":0,"k":0,"ix":4},"p":{"a":0,"k":[170.782,114.676],"ix":2},"r":{"a":0,"k":0,"ix":6},"sa":{"a":0,"k":0,"ix":5},"o":{"a":0,"k":100,"ix":7}}]},{"ty":"gr","bm":0,"hd":false,"mn":"ADBE Vector Group","nm":"Grupo 3","ix":3,"cix":2,"np":3,"it":[{"ty":"sh","bm":0,"hd":false,"mn":"ADBE Vector Shape - Group","nm":"Trazado 1","ix":1,"d":1,"ks":{"a":0,"k":{"c":false,"i":[[0,0],[0,0]],"o":[[0,0],[0,0]],"v":[[4.151,-4.151],[-4.151,4.151]]},"ix":2}},{"ty":"st","bm":0,"hd":false,"mn":"ADBE Vector Graphic - Stroke","nm":"Trazo 1","lc":2,"lj":1,"ml":10,"o":{"a":0,"k":100,"ix":4},"w":{"a":0,"k":1.5,"ix":5},"c":{"a":0,"k":[0.8275,0.1843,0.1843],"ix":3}},{"ty":"fl","bm":0,"hd":false,"mn":"ADBE Vector Graphic - Fill","nm":"Relleno 1","c":{"a":0,"k":[1,1,1],"ix":4},"r":1,"o":{"a":0,"k":100,"ix":5}},{"ty":"tr","a":{"a":0,"k":[0,0],"ix":1},"s":{"a":0,"k":[100,100],"ix":3},"sk":{"a":0,"k":0,"ix":4},"p":{"a":0,"k":[164.561,115.703],"ix":2},"r":{"a":0,"k":0,"ix":6},"sa":{"a":0,"k":0,"ix":5},"o":{"a":0,"k":100,"ix":7}}]},{"ty":"gr","bm":0,"hd":false,"mn":"ADBE Vector Group","nm":"Grupo 4","ix":4,"cix":2,"np":3,"it":[{"ty":"sh","bm":0,"hd":false,"mn":"ADBE Vector Shape - Group","nm":"Trazado 1","ix":1,"d":1,"ks":{"a":0,"k":{"c":true,"i":[[1.047,0],[0,0],[0,1.046],[0,0],[-1.047,0],[0,0],[0,-1.046],[0,0]],"o":[[0,0],[-1.047,0],[0,0],[0,-1.046],[0,0],[1.047,0],[0,0],[0,1.046]],"v":[[9.784,6.64],[-9.785,6.64],[-11.68,4.745],[-11.68,-4.746],[-9.785,-6.64],[9.784,-6.64],[11.68,-4.746],[11.68,4.745]]},"ix":2}},{"ty":"st","bm":0,"hd":false,"mn":"ADBE Vector Graphic - Stroke","nm":"Trazo 1","lc":2,"lj":1,"ml":10,"o":{"a":0,"k":100,"ix":4},"w":{"a":0,"k":1.5,"ix":5},"c":{"a":0,"k":[0.1098,0.1569,0.2],"ix":3}},{"ty":"fl","bm":0,"hd":false,"mn":"ADBE Vector Graphic - Fill","nm":"Relleno 1","c":{"a":0,"k":[1,1,1],"ix":4},"r":1,"o":{"a":0,"k":100,"ix":5}},{"ty":"tr","a":{"a":0,"k":[0,0],"ix":1},"s":{"a":0,"k":[100,100],"ix":3},"sk":{"a":0,"k":0,"ix":4},"p":{"a":0,"k":[171.966,115.787],"ix":2},"r":{"a":0,"k":0,"ix":6},"sa":{"a":0,"k":0,"ix":5},"o":{"a":0,"k":100,"ix":7}}]},{"ty":"gr","bm":0,"hd":false,"mn":"ADBE Vector Group","nm":"Grupo 5","ix":5,"cix":2,"np":3,"it":[{"ty":"sh","bm":0,"hd":false,"mn":"ADBE Vector Shape - Group","nm":"Trazado 1","ix":1,"d":1,"ks":{"a":0,"k":{"c":true,"i":[[1.047,0],[0,0],[0,-1.046],[0,0],[0,0],[0,0]],"o":[[0,0],[-1.047,0],[0,0],[0,0],[0,0],[0,-1.046]],"v":[[6.049,-14.329],[-6.05,-14.329],[-7.945,-12.434],[-7.945,14.329],[7.945,14.329],[7.945,-12.434]]},"ix":2}},{"ty":"st","bm":0,"hd":false,"mn":"ADBE Vector Graphic - Stroke","nm":"Trazo 1","lc":2,"lj":1,"ml":10,"o":{"a":0,"k":100,"ix":4},"w":{"a":0,"k":1.5,"ix":5},"c":{"a":0,"k":[0.1098,0.1569,0.2],"ix":3}},{"ty":"fl","bm":0,"hd":false,"mn":"ADBE Vector Graphic - Fill","nm":"Relleno 1","c":{"a":0,"k":[1,1,1],"ix":4},"r":1,"o":{"a":0,"k":100,"ix":5}},{"ty":"tr","a":{"a":0,"k":[0,0],"ix":1},"s":{"a":0,"k":[100,100],"ix":3},"sk":{"a":0,"k":0,"ix":4},"p":{"a":0,"k":[144.3,123.476],"ix":2},"r":{"a":0,"k":0,"ix":6},"sa":{"a":0,"k":0,"ix":5},"o":{"a":0,"k":100,"ix":7}}]},{"ty":"gr","bm":0,"hd":false,"mn":"ADBE Vector Group","nm":"Grupo 6","ix":6,"cix":2,"np":3,"it":[{"ty":"sh","bm":0,"hd":false,"mn":"ADBE Vector Shape - Group","nm":"Trazado 1","ix":1,"d":1,"ks":{"a":0,"k":{"c":true,"i":[[1.121,0],[0,0],[0,1.122],[0,0],[-1.122,0],[0,0],[0,-1.122],[0,0]],"o":[[0,0],[-1.122,0],[0,0],[0,-1.122],[0,0],[1.121,0],[0,0],[0,1.122]],"v":[[34.648,2.113],[-34.648,2.113],[-36.68,0.081],[-36.68,-0.081],[-34.648,-2.113],[34.648,-2.113],[36.679,-0.081],[36.679,0.081]]},"ix":2}},{"ty":"st","bm":0,"hd":false,"mn":"ADBE Vector Graphic - Stroke","nm":"Trazo 1","lc":2,"lj":1,"ml":10,"o":{"a":0,"k":100,"ix":4},"w":{"a":0,"k":1.5,"ix":5},"c":{"a":0,"k":[0.1098,0.1569,0.2],"ix":3}},{"ty":"fl","bm":0,"hd":false,"mn":"ADBE Vector Graphic - Fill","nm":"Relleno 1","c":{"a":0,"k":[1,1,1],"ix":4},"r":1,"o":{"a":0,"k":100,"ix":5}},{"ty":"tr","a":{"a":0,"k":[0,0],"ix":1},"s":{"a":0,"k":[100,100],"ix":3},"sk":{"a":0,"k":0,"ix":4},"p":{"a":0,"k":[160,78.531],"ix":2},"r":{"a":0,"k":0,"ix":6},"sa":{"a":0,"k":0,"ix":5},"o":{"a":0,"k":100,"ix":7}}]},{"ty":"gr","bm":0,"hd":false,"mn":"ADBE Vector Group","nm":"Grupo 7","ix":7,"cix":2,"np":2,"it":[{"ty":"sh","bm":0,"hd":false,"mn":"ADBE Vector Shape - Group","nm":"Trazado 1","ix":1,"d":1,"ks":{"a":0,"k":{"c":true,"i":[[4.421,0],[0,0],[0.576,4.138],[0,0],[0,0],[0,0]],"o":[[0,0],[-4.421,0],[0,0],[0,0],[0,0],[0.96,4.138]],"v":[[2.062,11.896],[2.062,11.896],[-7.007,4.248],[-9.253,-11.896],[4.549,-11.896],[8.292,4.248]]},"ix":2}},{"ty":"st","bm":0,"hd":false,"mn":"ADBE Vector Graphic - Stroke","nm":"Trazo 1","lc":2,"lj":1,"ml":10,"o":{"a":0,"k":100,"ix":4},"w":{"a":0,"k":1.5,"ix":5},"c":{"a":0,"k":[0.1098,0.1569,0.2],"ix":3}},{"ty":"tr","a":{"a":0,"k":[0,0],"ix":1},"s":{"a":0,"k":[100,100],"ix":3},"sk":{"a":0,"k":0,"ix":4},"p":{"a":0,"k":[189.957,92.54],"ix":2},"r":{"a":0,"k":0,"ix":6},"sa":{"a":0,"k":0,"ix":5},"o":{"a":0,"k":100,"ix":7}}]},{"ty":"gr","bm":0,"hd":false,"mn":"ADBE Vector Group","nm":"Grupo 8","ix":8,"cix":2,"np":2,"it":[{"ty":"sh","bm":0,"hd":false,"mn":"ADBE Vector Shape - Group","nm":"Trazado 1","ix":1,"d":1,"ks":{"a":0,"k":{"c":true,"i":[[4.421,0],[0,0],[0.191,4.138],[0,0],[0,0],[0,0]],"o":[[0,0],[-4.421,0],[0,0],[0,0],[0,0],[0.577,4.138]],"v":[[0.796,11.896],[0.796,11.896],[-7.564,4.248],[-8.312,-11.896],[5.489,-11.896],[7.735,4.248]]},"ix":2}},{"ty":"st","bm":0,"hd":false,"mn":"ADBE Vector Graphic - Stroke","nm":"Trazo 1","lc":2,"lj":1,"ml":10,"o":{"a":0,"k":100,"ix":4},"w":{"a":0,"k":1.5,"ix":5},"c":{"a":0,"k":[0.1098,0.1569,0.2],"ix":3}},{"ty":"tr","a":{"a":0,"k":[0,0],"ix":1},"s":{"a":0,"k":[100,100],"ix":3},"sk":{"a":0,"k":0,"ix":4},"p":{"a":0,"k":[175.214,92.54],"ix":2},"r":{"a":0,"k":0,"ix":6},"sa":{"a":0,"k":0,"ix":5},"o":{"a":0,"k":100,"ix":7}}]},{"ty":"gr","bm":0,"hd":false,"mn":"ADBE Vector Group","nm":"Grupo 9","ix":9,"cix":2,"np":2,"it":[{"ty":"sh","bm":0,"hd":false,"mn":"ADBE Vector Shape - Group","nm":"Trazado 1","ix":1,"d":1,"ks":{"a":0,"k":{"c":true,"i":[[4.421,0],[0,0],[-0.192,4.138],[0,0],[0,0],[0,0]],"o":[[0,0],[-4.421,0],[0,0],[0,0],[0,0],[0.192,4.138]],"v":[[0,11.896],[0,11.896],[-7.65,4.248],[-6.901,-11.896],[6.901,-11.896],[7.65,4.248]]},"ix":2}},{"ty":"st","bm":0,"hd":false,"mn":"ADBE Vector Graphic - Stroke","nm":"Trazo 1","lc":2,"lj":1,"ml":10,"o":{"a":0,"k":100,"ix":4},"w":{"a":0,"k":1.5,"ix":5},"c":{"a":0,"k":[0.1098,0.1569,0.2],"ix":3}},{"ty":"tr","a":{"a":0,"k":[0,0],"ix":1},"s":{"a":0,"k":[100,100],"ix":3},"sk":{"a":0,"k":0,"ix":4},"p":{"a":0,"k":[160,92.54],"ix":2},"r":{"a":0,"k":0,"ix":6},"sa":{"a":0,"k":0,"ix":5},"o":{"a":0,"k":100,"ix":7}}]},{"ty":"gr","bm":0,"hd":false,"mn":"ADBE Vector Group","nm":"Grupo 10","ix":10,"cix":2,"np":2,"it":[{"ty":"sh","bm":0,"hd":false,"mn":"ADBE Vector Shape - Group","nm":"Trazado 1","ix":1,"d":1,"ks":{"a":0,"k":{"c":true,"i":[[4.421,0],[0,0],[-0.577,4.138],[0,0],[0,0],[0,0]],"o":[[0,0],[-4.421,0],[0,0],[0,0],[0,0],[-0.193,4.138]],"v":[[-0.795,11.896],[-0.795,11.896],[-7.735,4.248],[-5.489,-11.896],[8.312,-11.896],[7.564,4.248]]},"ix":2}},{"ty":"st","bm":0,"hd":false,"mn":"ADBE Vector Graphic - Stroke","nm":"Trazo 1","lc":2,"lj":1,"ml":10,"o":{"a":0,"k":100,"ix":4},"w":{"a":0,"k":1.5,"ix":5},"c":{"a":0,"k":[0.1098,0.1569,0.2],"ix":3}},{"ty":"tr","a":{"a":0,"k":[0,0],"ix":1},"s":{"a":0,"k":[100,100],"ix":3},"sk":{"a":0,"k":0,"ix":4},"p":{"a":0,"k":[144.786,92.54],"ix":2},"r":{"a":0,"k":0,"ix":6},"sa":{"a":0,"k":0,"ix":5},"o":{"a":0,"k":100,"ix":7}}]},{"ty":"gr","bm":0,"hd":false,"mn":"ADBE Vector Group","nm":"Grupo 11","ix":11,"cix":2,"np":2,"it":[{"ty":"sh","bm":0,"hd":false,"mn":"ADBE Vector Shape - Group","nm":"Trazado 1","ix":1,"d":1,"ks":{"a":0,"k":{"c":true,"i":[[4.421,0],[0,0],[-0.96,4.138],[0,0],[0,0],[0,0]],"o":[[0,0],[-4.421,0],[0,0],[0,0],[0,0],[-0.576,4.138]],"v":[[-2.062,11.896],[-2.062,11.896],[-8.293,4.248],[-4.549,-11.896],[9.253,-11.896],[7.007,4.248]]},"ix":2}},{"ty":"st","bm":0,"hd":false,"mn":"ADBE Vector Graphic - Stroke","nm":"Trazo 1","lc":2,"lj":1,"ml":10,"o":{"a":0,"k":100,"ix":4},"w":{"a":0,"k":1.5,"ix":5},"c":{"a":0,"k":[0.1098,0.1569,0.2],"ix":3}},{"ty":"tr","a":{"a":0,"k":[0,0],"ix":1},"s":{"a":0,"k":[100,100],"ix":3},"sk":{"a":0,"k":0,"ix":4},"p":{"a":0,"k":[130.042,92.54],"ix":2},"r":{"a":0,"k":0,"ix":6},"sa":{"a":0,"k":0,"ix":5},"o":{"a":0,"k":100,"ix":7}}]},{"ty":"gr","bm":0,"hd":false,"mn":"ADBE Vector Group","nm":"Grupo 12","ix":12,"cix":2,"np":4,"it":[{"ty":"sh","bm":0,"hd":false,"mn":"ADBE Vector Shape - Group","nm":"Trazado 1","ix":1,"d":1,"ks":{"a":0,"k":{"c":true,"i":[[0,0],[0,0],[0,0],[-4.421,0],[0.96,4.138]],"o":[[0,0],[0,0],[0.577,4.138],[4.421,0],[0,0]],"v":[[4.55,-11.896],[-9.253,-11.896],[-7.007,4.247],[2.063,11.896],[8.293,4.247]]},"ix":2}},{"ty":"sh","bm":0,"hd":false,"mn":"ADBE Vector Shape - Group","nm":"Trazado 2","ix":2,"d":1,"ks":{"a":0,"k":{"c":true,"i":[[0,0],[0,0],[0.573,-0.721],[1.212,0],[0.375,2.699],[0,0]],"o":[[0,0],[0.252,1.085],[-0.6,0.756],[-2.873,0],[0,0],[0,0]],"v":[[2.166,-8.896],[5.371,4.924],[4.873,7.726],[2.063,8.896],[-4.035,3.833],[-5.806,-8.896]]},"ix":2}},{"ty":"mm","bm":0,"hd":false,"mn":"ADBE Vector Filter - Merge","nm":"Combinar trazados 1","mm":1},{"ty":"fl","bm":0,"hd":false,"mn":"ADBE Vector Graphic - Fill","nm":"Relleno 1","c":{"a":0,"k":[1,1,1],"ix":4},"r":1,"o":{"a":0,"k":100,"ix":5}},{"ty":"tr","a":{"a":0,"k":[0,0],"ix":1},"s":{"a":0,"k":[100,100],"ix":3},"sk":{"a":0,"k":0,"ix":4},"p":{"a":0,"k":[189.957,92.54],"ix":2},"r":{"a":0,"k":0,"ix":6},"sa":{"a":0,"k":0,"ix":5},"o":{"a":0,"k":100,"ix":7}}]},{"ty":"gr","bm":0,"hd":false,"mn":"ADBE Vector Group","nm":"Grupo 13","ix":13,"cix":2,"np":2,"it":[{"ty":"sh","bm":0,"hd":false,"mn":"ADBE Vector Shape - Group","nm":"Trazado 1","ix":1,"d":1,"ks":{"a":0,"k":{"c":true,"i":[[1.679,0],[0.48,3.445],[0,0],[0,0],[0,0],[0.864,-1.086]],"o":[[-3.631,0],[0,0],[0,0],[0,0],[0.356,1.54],[-0.89,1.121]],"v":[[2.233,10.396],[-5.351,4.041],[-7.359,-10.396],[3.528,-10.396],[7.003,4.586],[6.217,8.659]]},"ix":2}},{"ty":"fl","bm":0,"hd":false,"mn":"ADBE Vector Graphic - Fill","nm":"Relleno 1","c":{"a":0,"k":[0.298,0.6863,0.3137],"ix":4},"r":1,"o":{"a":0,"k":100,"ix":5}},{"ty":"tr","a":{"a":0,"k":[0,0],"ix":1},"s":{"a":0,"k":[100,100],"ix":3},"sk":{"a":0,"k":0,"ix":4},"p":{"a":0,"k":[189.786,92.54],"ix":2},"r":{"a":0,"k":0,"ix":6},"sa":{"a":0,"k":0,"ix":5},"o":{"a":0,"k":100,"ix":7}}]},{"ty":"gr","bm":0,"hd":false,"mn":"ADBE Vector Group","nm":"Grupo 14","ix":14,"cix":2,"np":4,"it":[{"ty":"sh","bm":0,"hd":false,"mn":"ADBE Vector Shape - Group","nm":"Trazado 1","ix":1,"d":1,"ks":{"a":0,"k":{"c":true,"i":[[0,0],[0,0],[0,0],[-4.421,0],[0.576,4.138]],"o":[[0,0],[0,0],[0.192,4.138],[4.421,0],[0,0]],"v":[[5.491,-11.896],[-8.312,-11.896],[-7.563,4.247],[0.797,11.896],[7.736,4.247]]},"ix":2}},{"ty":"sh","bm":0,"hd":false,"mn":"ADBE Vector Shape - Group","nm":"Trazado 2","ix":2,"d":1,"ks":{"a":0,"k":{"c":true,"i":[[0,0],[0,0],[0.681,-0.783],[1.29,0],[0.121,2.597],[0,0]],"o":[[0,0],[0.154,1.098],[-0.741,0.851],[-2.786,0],[0,0],[0,0]],"v":[[2.88,-8.896],[4.764,4.661],[3.947,7.577],[0.797,8.896],[-4.568,4.107],[-5.169,-8.896]]},"ix":2}},{"ty":"mm","bm":0,"hd":false,"mn":"ADBE Vector Filter - Merge","nm":"Combinar trazados 1","mm":1},{"ty":"fl","bm":0,"hd":false,"mn":"ADBE Vector Graphic - Fill","nm":"Relleno 1","c":{"a":0,"k":[1,1,1],"ix":4},"r":1,"o":{"a":0,"k":100,"ix":5}},{"ty":"tr","a":{"a":0,"k":[0,0],"ix":1},"s":{"a":0,"k":[100,100],"ix":3},"sk":{"a":0,"k":0,"ix":4},"p":{"a":0,"k":[175.214,92.54],"ix":2},"r":{"a":0,"k":0,"ix":6},"sa":{"a":0,"k":0,"ix":5},"o":{"a":0,"k":100,"ix":7}}]},{"ty":"gr","bm":0,"hd":false,"mn":"ADBE Vector Group","nm":"Grupo 15","ix":15,"cix":2,"np":2,"it":[{"ty":"sh","bm":0,"hd":false,"mn":"ADBE Vector Shape - Group","nm":"Trazado 1","ix":1,"d":1,"ks":{"a":0,"k":{"c":true,"i":[[1.73,0],[0.156,3.371],[0,0],[0,0],[0,0],[0.97,-1.113]],"o":[[-3.563,0],[0,0],[0,0],[0,0],[0.213,1.534],[-1.03,1.185]],"v":[[0.935,10.396],[-5.926,4.177],[-6.602,-10.396],[4.324,-10.396],[6.389,4.454],[5.217,8.56]]},"ix":2}},{"ty":"fl","bm":0,"hd":false,"mn":"ADBE Vector Graphic - Fill","nm":"Relleno 1","c":{"a":0,"k":[0.298,0.6863,0.3137],"ix":4},"r":1,"o":{"a":0,"k":100,"ix":5}},{"ty":"tr","a":{"a":0,"k":[0,0],"ix":1},"s":{"a":0,"k":[100,100],"ix":3},"sk":{"a":0,"k":0,"ix":4},"p":{"a":0,"k":[175.075,92.54],"ix":2},"r":{"a":0,"k":0,"ix":6},"sa":{"a":0,"k":0,"ix":5},"o":{"a":0,"k":100,"ix":7}}]},{"ty":"gr","bm":0,"hd":false,"mn":"ADBE Vector Group","nm":"Grupo 16","ix":16,"cix":2,"np":4,"it":[{"ty":"sh","bm":0,"hd":false,"mn":"ADBE Vector Shape - Group","nm":"Trazado 1","ix":1,"d":1,"ks":{"a":0,"k":{"c":true,"i":[[0,0],[0,0],[0,0],[-4.421,0],[0.191,4.138]],"o":[[0,0],[0,0],[-0.193,4.138],[4.421,0],[0,0]],"v":[[6.902,-11.896],[-6.901,-11.896],[-7.649,4.247],[0.001,11.896],[7.651,4.247]]},"ix":2}},{"ty":"sh","bm":0,"hd":false,"mn":"ADBE Vector Shape - Group","nm":"Trazado 2","ix":2,"d":1,"ks":{"a":0,"k":{"c":true,"i":[[0,0],[0,0],[0.807,-0.845],[1.356,0],[0.891,0.932],[-0.052,1.132],[0,0]],"o":[[0,0],[0.053,1.132],[-0.891,0.932],[-1.357,0],[-0.806,-0.845],[0,0],[0,0]],"v":[[4.038,-8.896],[4.654,4.385],[3.485,7.451],[0.001,8.896],[-3.484,7.451],[-4.653,4.385],[-4.036,-8.896]]},"ix":2}},{"ty":"mm","bm":0,"hd":false,"mn":"ADBE Vector Filter - Merge","nm":"Combinar trazados 1","mm":1},{"ty":"fl","bm":0,"hd":false,"mn":"ADBE Vector Graphic - Fill","nm":"Relleno 1","c":{"a":0,"k":[1,1,1],"ix":4},"r":1,"o":{"a":0,"k":100,"ix":5}},{"ty":"tr","a":{"a":0,"k":[0,0],"ix":1},"s":{"a":0,"k":[100,100],"ix":3},"sk":{"a":0,"k":0,"ix":4},"p":{"a":0,"k":[159.999,92.54],"ix":2},"r":{"a":0,"k":0,"ix":6},"sa":{"a":0,"k":0,"ix":5},"o":{"a":0,"k":100,"ix":7}}]},{"ty":"gr","bm":0,"hd":false,"mn":"ADBE Vector Group","nm":"Grupo 17","ix":17,"cix":2,"np":2,"it":[{"ty":"sh","bm":0,"hd":false,"mn":"ADBE Vector Shape - Group","nm":"Trazado 1","ix":1,"d":1,"ks":{"a":0,"k":{"c":true,"i":[[1.771,0],[1.176,1.232],[-0.072,1.545],[0,0],[0,0],[0,0],[1.092,-1.144]],"o":[[-1.771,0],[-1.092,-1.144],[0,0],[0,0],[0,0],[0.072,1.545],[-1.176,1.232]],"v":[[0,10.396],[-4.57,8.486],[-6.151,4.317],[-5.469,-10.396],[5.469,-10.396],[6.152,4.317],[4.568,8.486]]},"ix":2}},{"ty":"fl","bm":0,"hd":false,"mn":"ADBE Vector Graphic - Fill","nm":"Relleno 1","c":{"a":0,"k":[0.298,0.6863,0.3137],"ix":4},"r":1,"o":{"a":0,"k":100,"ix":5}},{"ty":"tr","a":{"a":0,"k":[0,0],"ix":1},"s":{"a":0,"k":[100,100],"ix":3},"sk":{"a":0,"k":0,"ix":4},"p":{"a":0,"k":[160,92.54],"ix":2},"r":{"a":0,"k":0,"ix":6},"sa":{"a":0,"k":0,"ix":5},"o":{"a":0,"k":100,"ix":7}}]},{"ty":"gr","bm":0,"hd":false,"mn":"ADBE Vector Group","nm":"Grupo 18","ix":18,"cix":2,"np":4,"it":[{"ty":"sh","bm":0,"hd":false,"mn":"ADBE Vector Shape - Group","nm":"Trazado 1","ix":1,"d":1,"ks":{"a":0,"k":{"c":true,"i":[[0,0],[0,0],[0,0],[-4.421,0],[-0.192,4.138]],"o":[[0,0],[0,0],[-0.576,4.138],[4.421,0],[0,0]],"v":[[8.312,-11.896],[-5.491,-11.896],[-7.737,4.247],[-0.796,11.896],[7.563,4.247]]},"ix":2}},{"ty":"sh","bm":0,"hd":false,"mn":"ADBE Vector Shape - Group","nm":"Trazado 2","ix":2,"d":1,"ks":{"a":0,"k":{"c":true,"i":[[0,0],[0,0],[2.786,0],[0.741,0.851],[-0.152,1.098],[0,0]],"o":[[0,0],[-0.12,2.597],[-1.29,0],[-0.681,-0.783],[0,0],[0,0]],"v":[[5.17,-8.896],[4.566,4.107],[-0.796,8.896],[-3.947,7.577],[-4.766,4.661],[-2.879,-8.896]]},"ix":2}},{"ty":"mm","bm":0,"hd":false,"mn":"ADBE Vector Filter - Merge","nm":"Combinar trazados 1","mm":1},{"ty":"fl","bm":0,"hd":false,"mn":"ADBE Vector Graphic - Fill","nm":"Relleno 1","c":{"a":0,"k":[1,1,1],"ix":4},"r":1,"o":{"a":0,"k":100,"ix":5}},{"ty":"tr","a":{"a":0,"k":[0,0],"ix":1},"s":{"a":0,"k":[100,100],"ix":3},"sk":{"a":0,"k":0,"ix":4},"p":{"a":0,"k":[144.786,92.54],"ix":2},"r":{"a":0,"k":0,"ix":6},"sa":{"a":0,"k":0,"ix":5},"o":{"a":0,"k":100,"ix":7}}]},{"ty":"gr","bm":0,"hd":false,"mn":"ADBE Vector Group","nm":"Grupo 19","ix":19,"cix":2,"np":2,"it":[{"ty":"sh","bm":0,"hd":false,"mn":"ADBE Vector Shape - Group","nm":"Trazado 1","ix":1,"d":1,"ks":{"a":0,"k":{"c":true,"i":[[3.563,0],[1.031,1.185],[-0.213,1.534],[0,0],[0,0],[0,0]],"o":[[-1.731,0],[-0.969,-1.113],[0,0],[0,0],[0,0],[-0.156,3.371]],"v":[[-0.934,10.396],[-5.217,8.56],[-6.389,4.454],[-4.323,-10.396],[6.603,-10.396],[5.927,4.177]]},"ix":2}},{"ty":"fl","bm":0,"hd":false,"mn":"ADBE Vector Graphic - Fill","nm":"Relleno 1","c":{"a":0,"k":[0.298,0.6863,0.3137],"ix":4},"r":1,"o":{"a":0,"k":100,"ix":5}},{"ty":"tr","a":{"a":0,"k":[0,0],"ix":1},"s":{"a":0,"k":[100,100],"ix":3},"sk":{"a":0,"k":0,"ix":4},"p":{"a":0,"k":[144.925,92.54],"ix":2},"r":{"a":0,"k":0,"ix":6},"sa":{"a":0,"k":0,"ix":5},"o":{"a":0,"k":100,"ix":7}}]},{"ty":"gr","bm":0,"hd":false,"mn":"ADBE Vector Group","nm":"Grupo 20","ix":20,"cix":2,"np":4,"it":[{"ty":"sh","bm":0,"hd":false,"mn":"ADBE Vector Shape - Group","nm":"Trazado 1","ix":1,"d":1,"ks":{"a":0,"k":{"c":true,"i":[[0,0],[0,0],[0,0],[-4.422,0],[-0.576,4.138]],"o":[[0,0],[0,0],[-0.96,4.138],[4.42,0],[0,0]],"v":[[9.253,-11.896],[-4.549,-11.896],[-8.293,4.247],[-2.062,11.896],[7.007,4.247]]},"ix":2}},{"ty":"sh","bm":0,"hd":false,"mn":"ADBE Vector Shape - Group","nm":"Trazado 2","ix":2,"d":1,"ks":{"a":0,"k":{"c":true,"i":[[0,0],[0,0],[2.873,0],[0.6,0.756],[-0.251,1.085],[0,0]],"o":[[0,0],[-0.375,2.699],[-1.212,0],[-0.574,-0.721],[0,0],[0,0]],"v":[[5.807,-8.896],[4.035,3.833],[-2.062,8.896],[-4.872,7.726],[-5.371,4.924],[-2.165,-8.896]]},"ix":2}},{"ty":"mm","bm":0,"hd":false,"mn":"ADBE Vector Filter - Merge","nm":"Combinar trazados 1","mm":1},{"ty":"fl","bm":0,"hd":false,"mn":"ADBE Vector Graphic - Fill","nm":"Relleno 1","c":{"a":0,"k":[1,1,1],"ix":4},"r":1,"o":{"a":0,"k":100,"ix":5}},{"ty":"tr","a":{"a":0,"k":[0,0],"ix":1},"s":{"a":0,"k":[100,100],"ix":3},"sk":{"a":0,"k":0,"ix":4},"p":{"a":0,"k":[130.043,92.54],"ix":2},"r":{"a":0,"k":0,"ix":6},"sa":{"a":0,"k":0,"ix":5},"o":{"a":0,"k":100,"ix":7}}]},{"ty":"gr","bm":0,"hd":false,"mn":"ADBE Vector Group","nm":"Grupo 21","ix":21,"cix":2,"np":2,"it":[{"ty":"sh","bm":0,"hd":false,"mn":"ADBE Vector Shape - Group","nm":"Trazado 1","ix":1,"d":1,"ks":{"a":0,"k":{"c":true,"i":[[3.631,0],[0.891,1.121],[-0.357,1.54],[0,0],[0,0],[0,0]],"o":[[-1.679,0],[-0.863,-1.086],[0,0],[0,0],[0,0],[-0.479,3.445]],"v":[[-2.232,10.396],[-6.217,8.659],[-7.003,4.586],[-3.528,-10.396],[7.359,-10.396],[5.35,4.041]]},"ix":2}},{"ty":"fl","bm":0,"hd":false,"mn":"ADBE Vector Graphic - Fill","nm":"Relleno 1","c":{"a":0,"k":[0.298,0.6863,0.3137],"ix":4},"r":1,"o":{"a":0,"k":100,"ix":5}},{"ty":"tr","a":{"a":0,"k":[0,0],"ix":1},"s":{"a":0,"k":[100,100],"ix":3},"sk":{"a":0,"k":0,"ix":4},"p":{"a":0,"k":[130.213,92.54],"ix":2},"r":{"a":0,"k":0,"ix":6},"sa":{"a":0,"k":0,"ix":5},"o":{"a":0,"k":100,"ix":7}}]},{"ty":"gr","bm":0,"hd":false,"mn":"ADBE Vector Group","nm":"Grupo 22","ix":22,"cix":2,"np":2,"it":[{"ty":"sh","bm":0,"hd":false,"mn":"ADBE Vector Shape - Group","nm":"Trazado 1","ix":1,"d":1,"ks":{"a":0,"k":{"c":true,"i":[[2.094,0],[0,0],[0,2.094],[0,0],[-2.093,0],[0,0],[0,-2.093],[0,0]],"o":[[0,0],[-2.093,0],[0,0],[0,-2.093],[0,0],[2.094,0],[0,0],[0,2.094]],"v":[[30.715,25.023],[-30.717,25.023],[-34.507,21.234],[-34.507,-21.234],[-30.717,-25.023],[30.715,-25.023],[34.506,-21.234],[34.506,21.234]]},"ix":2}},{"ty":"st","bm":0,"hd":false,"mn":"ADBE Vector Graphic - Stroke","nm":"Trazo 1","lc":2,"lj":1,"ml":10,"o":{"a":0,"k":100,"ix":4},"w":{"a":0,"k":1.5,"ix":5},"c":{"a":0,"k":[0.1098,0.1569,0.2],"ix":3}},{"ty":"tr","a":{"a":0,"k":[0,0],"ix":1},"s":{"a":0,"k":[100,100],"ix":3},"sk":{"a":0,"k":0,"ix":4},"p":{"a":0,"k":[160,112.781],"ix":2},"r":{"a":0,"k":0,"ix":6},"sa":{"a":0,"k":0,"ix":5},"o":{"a":0,"k":100,"ix":7}}]}],"ind":2},{"ty":4,"nm":"fondo/loading place contornos","sr":1,"st":0,"op":104,"ip":0,"hd":false,"ddd":0,"bm":0,"hasMask":false,"ao":0,"ks":{"a":{"a":0,"k":[160,80,0],"ix":1},"s":{"a":0,"k":[100,100,100],"ix":6},"sk":{"a":0,"k":0},"p":{"a":0,"k":[160,80,0],"ix":2},"r":{"a":0,"k":0,"ix":10},"sa":{"a":0,"k":0},"o":{"a":0,"k":100,"ix":11}},"ef":[],"shapes":[{"ty":"gr","bm":0,"hd":false,"mn":"ADBE Vector Group","nm":"Grupo 1","ix":1,"cix":2,"np":2,"it":[{"ty":"sh","bm":0,"hd":false,"mn":"ADBE Vector Shape - Group","nm":"Trazado 1","ix":1,"d":1,"ks":{"a":0,"k":{"c":false,"i":[[0,0],[0,0]],"o":[[0,0],[0,0]],"v":[[73.539,137.805],[66.798,137.805]]},"ix":2}},{"ty":"st","bm":0,"hd":false,"mn":"ADBE Vector Graphic - Stroke","nm":"Trazo 1","lc":2,"lj":1,"ml":10,"o":{"a":0,"k":100,"ix":4},"w":{"a":0,"k":1.5,"ix":5},"c":{"a":0,"k":[0.1098,0.1569,0.2],"ix":3}},{"ty":"tr","a":{"a":0,"k":[0,0],"ix":1},"s":{"a":0,"k":[100,100],"ix":3},"sk":{"a":0,"k":0,"ix":4},"p":{"a":0,"k":[0,0],"ix":2},"r":{"a":0,"k":0,"ix":6},"sa":{"a":0,"k":0,"ix":5},"o":{"a":0,"k":100,"ix":7}}]},{"ty":"gr","bm":0,"hd":false,"mn":"ADBE Vector Group","nm":"Grupo 2","ix":2,"cix":2,"np":2,"it":[{"ty":"sh","bm":0,"hd":false,"mn":"ADBE Vector Shape - Group","nm":"Trazado 1","ix":1,"d":1,"ks":{"a":0,"k":{"c":false,"i":[[0,0],[0,0]],"o":[[0,0],[0,0]],"v":[[61.911,137.805],[55.17,137.805]]},"ix":2}},{"ty":"st","bm":0,"hd":false,"mn":"ADBE Vector Graphic - Stroke","nm":"Trazo 1","lc":2,"lj":1,"ml":10,"o":{"a":0,"k":100,"ix":4},"w":{"a":0,"k":1.5,"ix":5},"c":{"a":0,"k":[0.1098,0.1569,0.2],"ix":3}},{"ty":"tr","a":{"a":0,"k":[0,0],"ix":1},"s":{"a":0,"k":[100,100],"ix":3},"sk":{"a":0,"k":0,"ix":4},"p":{"a":0,"k":[0,0],"ix":2},"r":{"a":0,"k":0,"ix":6},"sa":{"a":0,"k":0,"ix":5},"o":{"a":0,"k":100,"ix":7}}]},{"ty":"gr","bm":0,"hd":false,"mn":"ADBE Vector Group","nm":"Grupo 3","ix":3,"cix":2,"np":2,"it":[{"ty":"sh","bm":0,"hd":false,"mn":"ADBE Vector Shape - Group","nm":"Trazado 1","ix":1,"d":1,"ks":{"a":0,"k":{"c":false,"i":[[0,0],[0,0]],"o":[[0,0],[0,0]],"v":[[264.83,137.805],[249.286,137.805]]},"ix":2}},{"ty":"st","bm":0,"hd":false,"mn":"ADBE Vector Graphic - Stroke","nm":"Trazo 1","lc":2,"lj":1,"ml":10,"o":{"a":0,"k":100,"ix":4},"w":{"a":0,"k":1.5,"ix":5},"c":{"a":0,"k":[0.1098,0.1569,0.2],"ix":3}},{"ty":"tr","a":{"a":0,"k":[0,0],"ix":1},"s":{"a":0,"k":[100,100],"ix":3},"sk":{"a":0,"k":0,"ix":4},"p":{"a":0,"k":[0,0],"ix":2},"r":{"a":0,"k":0,"ix":6},"sa":{"a":0,"k":0,"ix":5},"o":{"a":0,"k":100,"ix":7}}]},{"ty":"gr","bm":0,"hd":false,"mn":"ADBE Vector Group","nm":"Grupo 4","ix":4,"cix":2,"np":2,"it":[{"ty":"sh","bm":0,"hd":false,"mn":"ADBE Vector Shape - Group","nm":"Trazado 1","ix":1,"d":1,"ks":{"a":0,"k":{"c":false,"i":[[0,0],[0,0]],"o":[[0,0],[0,0]],"v":[[79.224,137.805],[238.171,137.805]]},"ix":2}},{"ty":"st","bm":0,"hd":false,"mn":"ADBE Vector Graphic - Stroke","nm":"Trazo 1","lc":2,"lj":1,"ml":10,"o":{"a":0,"k":100,"ix":4},"w":{"a":0,"k":1.5,"ix":5},"c":{"a":0,"k":[0.1098,0.1569,0.2],"ix":3}},{"ty":"tr","a":{"a":0,"k":[0,0],"ix":1},"s":{"a":0,"k":[100,100],"ix":3},"sk":{"a":0,"k":0,"ix":4},"p":{"a":0,"k":[0,0],"ix":2},"r":{"a":0,"k":0,"ix":6},"sa":{"a":0,"k":0,"ix":5},"o":{"a":0,"k":100,"ix":7}}]}],"ind":3},{"ty":1,"nm":"Sólido Blanco 2","sr":1,"st":0,"op":110,"ip":0,"hd":false,"ddd":0,"bm":0,"hasMask":false,"ao":0,"ks":{"a":{"a":0,"k":[160,80,0],"ix":1},"s":{"a":0,"k":[100,100,100],"ix":6},"sk":{"a":0,"k":0},"p":{"a":0,"k":[160,217,0],"ix":2},"r":{"a":0,"k":0,"ix":10},"sa":{"a":0,"k":0},"o":{"a":0,"k":100,"ix":11}},"ef":[],"sc":"#ffffff","sh":160,"sw":320,"ind":4},{"ty":4,"nm":"chack contornos","sr":1,"st":0,"op":104,"ip":0,"hd":false,"ddd":0,"bm":0,"hasMask":false,"ao":0,"ks":{"a":{"a":0,"k":[160,134.25,0],"ix":1},"s":{"a":0,"k":[100,100,100],"ix":6},"sk":{"a":0,"k":0},"p":{"a":0,"k":[160,137,0],"ix":2},"r":{"a":1,"k":[{"o":{"x":0.333,"y":0},"i":{"x":0.667,"y":1},"s":[-103],"t":66},{"o":{"x":0.333,"y":0},"i":{"x":0.667,"y":1},"s":[7],"t":77},{"o":{"x":0.167,"y":0},"i":{"x":0.667,"y":1},"s":[0],"t":81},{"o":{"x":0.333,"y":0},"i":{"x":0.667,"y":1},"s":[0],"t":89},{"o":{"x":0.333,"y":0},"i":{"x":0.667,"y":1},"s":[-10],"t":93},{"s":[117],"t":103}],"ix":10},"sa":{"a":0,"k":0},"o":{"a":0,"k":100,"ix":11}},"ef":[],"shapes":[{"ty":"gr","bm":0,"hd":false,"mn":"ADBE Vector Group","nm":"Grupo 1","ix":1,"cix":2,"np":3,"it":[{"ty":"sh","bm":0,"hd":false,"mn":"ADBE Vector Shape - Group","nm":"Trazado 1","ix":1,"d":1,"ks":{"a":0,"k":{"c":false,"i":[[0,0],[0,0],[0,0]],"o":[[0,0],[0,0],[0,0]],"v":[[-7.356,-0.078],[-1.41,4.685],[7.357,-4.685]]},"ix":2}},{"ty":"st","bm":0,"hd":false,"mn":"ADBE Vector Graphic - Stroke","nm":"Trazo 1","lc":2,"lj":1,"ml":10,"o":{"a":0,"k":100,"ix":4},"w":{"a":0,"k":3,"ix":5},"c":{"a":0,"k":[1,1,1],"ix":3}},{"ty":"fl","bm":0,"hd":false,"mn":"ADBE Vector Graphic - Fill","nm":"Relleno 1","c":{"a":0,"k":[0.1098,0.1569,0.2],"ix":4},"r":1,"o":{"a":0,"k":100,"ix":5}},{"ty":"tr","a":{"a":0,"k":[0,0],"ix":1},"s":{"a":0,"k":[100,100],"ix":3},"sk":{"a":0,"k":0,"ix":4},"p":{"a":0,"k":[160,42.087],"ix":2},"r":{"a":0,"k":0,"ix":6},"sa":{"a":0,"k":0,"ix":5},"o":{"a":0,"k":100,"ix":7}}]},{"ty":"gr","bm":0,"hd":false,"mn":"ADBE Vector Group","nm":"Grupo 2","ix":2,"cix":2,"np":2,"it":[{"ty":"sh","bm":0,"hd":false,"mn":"ADBE Vector Shape - Group","nm":"Trazado 1","ix":1,"d":1,"ks":{"a":0,"k":{"c":true,"i":[[0,9.455],[9.454,0],[0,-9.455],[-9.455,0]],"o":[[0,-9.455],[-9.455,0],[0,9.455],[9.454,0]],"v":[[17.119,0],[0,-17.119],[-17.119,0],[0,17.119]]},"ix":2}},{"ty":"st","bm":0,"hd":false,"mn":"ADBE Vector Graphic - Stroke","nm":"Trazo 1","lc":2,"lj":2,"ml":1,"o":{"a":0,"k":100,"ix":4},"w":{"a":0,"k":1.3,"ix":5},"c":{"a":0,"k":[0.1098,0.1569,0.2],"ix":3}},{"ty":"tr","a":{"a":0,"k":[0,0],"ix":1},"s":{"a":0,"k":[100,100],"ix":3},"sk":{"a":0,"k":0,"ix":4},"p":{"a":0,"k":[160,42.087],"ix":2},"r":{"a":0,"k":0,"ix":6},"sa":{"a":0,"k":0,"ix":5},"o":{"a":0,"k":100,"ix":7}}]},{"ty":"gr","bm":0,"hd":false,"mn":"ADBE Vector Group","nm":"Grupo 3","ix":3,"cix":2,"np":4,"it":[{"ty":"sh","bm":0,"hd":false,"mn":"ADBE Vector Shape - Group","nm":"Trazado 1","ix":1,"d":1,"ks":{"a":0,"k":{"c":true,"i":[[9.454,0],[0,-9.454],[-9.455,0],[0,9.455]],"o":[[-9.455,0],[0,9.455],[9.454,0],[0,-9.454]],"v":[[0,-17.119],[-17.119,0],[0,17.119],[17.119,0]]},"ix":2}},{"ty":"sh","bm":0,"hd":false,"mn":"ADBE Vector Shape - Group","nm":"Trazado 2","ix":2,"d":1,"ks":{"a":0,"k":{"c":true,"i":[[-8.319,0],[0,-8.319],[8.319,0],[0,8.319]],"o":[[8.319,0],[0,8.319],[-8.319,0],[0,-8.319]],"v":[[0,-15.087],[15.087,0],[0,15.087],[-15.087,0]]},"ix":2}},{"ty":"mm","bm":0,"hd":false,"mn":"ADBE Vector Filter - Merge","nm":"Combinar trazados 1","mm":1},{"ty":"fl","bm":0,"hd":false,"mn":"ADBE Vector Graphic - Fill","nm":"Relleno 1","c":{"a":0,"k":[1,1,1],"ix":4},"r":1,"o":{"a":0,"k":100,"ix":5}},{"ty":"tr","a":{"a":0,"k":[0,0],"ix":1},"s":{"a":0,"k":[100,100],"ix":3},"sk":{"a":0,"k":0,"ix":4},"p":{"a":0,"k":[160,42.087],"ix":2},"r":{"a":0,"k":0,"ix":6},"sa":{"a":0,"k":0,"ix":5},"o":{"a":0,"k":100,"ix":7}}]},{"ty":"gr","bm":0,"hd":false,"mn":"ADBE Vector Group","nm":"Grupo 4","ix":4,"cix":2,"np":2,"it":[{"ty":"sh","bm":0,"hd":false,"mn":"ADBE Vector Shape - Group","nm":"Trazado 1","ix":1,"d":1,"ks":{"a":0,"k":{"c":true,"i":[[8.879,0],[0,8.879],[-8.879,0],[0,-8.879]],"o":[[-8.879,0],[0,-8.879],[8.879,0],[0,8.879]],"v":[[0,16.103],[-16.104,0],[0,-16.103],[16.104,0]]},"ix":2}},{"ty":"fl","bm":0,"hd":false,"mn":"ADBE Vector Graphic - Fill","nm":"Relleno 1","c":{"a":0,"k":[0.1098,0.1569,0.2],"ix":4},"r":1,"o":{"a":0,"k":100,"ix":5}},{"ty":"tr","a":{"a":0,"k":[0,0],"ix":1},"s":{"a":0,"k":[100,100],"ix":3},"sk":{"a":0,"k":0,"ix":4},"p":{"a":0,"k":[160,42.087],"ix":2},"r":{"a":0,"k":0,"ix":6},"sa":{"a":0,"k":0,"ix":5},"o":{"a":0,"k":100,"ix":7}}]}],"ind":5},{"ty":4,"nm":"money contornos","sr":1,"st":0,"op":100,"ip":0,"hd":false,"ddd":0,"bm":0,"hasMask":false,"ao":0,"ks":{"a":{"a":0,"k":[160,139,0],"ix":1},"s":{"a":0,"k":[100,100,100],"ix":6},"sk":{"a":0,"k":0},"p":{"a":0,"k":[160,137,0],"ix":2},"r":{"a":1,"k":[{"o":{"x":0.333,"y":0},"i":{"x":0.667,"y":1},"s":[-103],"t":33},{"o":{"x":0.333,"y":0},"i":{"x":0.667,"y":1},"s":[7],"t":44},{"o":{"x":0.167,"y":0},"i":{"x":0.667,"y":1},"s":[0],"t":48},{"o":{"x":0.333,"y":0},"i":{"x":0.667,"y":1},"s":[0],"t":56},{"o":{"x":0.333,"y":0},"i":{"x":0.667,"y":1},"s":[-10],"t":60},{"s":[117],"t":70}],"ix":10},"sa":{"a":0,"k":0},"o":{"a":0,"k":99,"ix":11}},"ef":[],"shapes":[{"ty":"gr","bm":0,"hd":false,"mn":"ADBE Vector Group","nm":"Grupo 1","ix":1,"cix":2,"np":2,"it":[{"ty":"sh","bm":0,"hd":false,"mn":"ADBE Vector Shape - Group","nm":"Trazado 1","ix":1,"d":1,"ks":{"a":0,"k":{"c":true,"i":[[-0.202,1.39],[1.39,0.202],[0.202,-1.391],[-1.39,-0.202]],"o":[[0.202,-1.391],[-1.391,-0.201],[-0.202,1.39],[1.391,0.202]],"v":[[2.518,0.365],[0.367,-2.518],[-2.518,-0.365],[-0.366,2.518]]},"ix":2}},{"ty":"fl","bm":0,"hd":false,"mn":"ADBE Vector Graphic - Fill","nm":"Relleno 1","c":{"a":0,"k":[1,1,1],"ix":4},"r":1,"o":{"a":0,"k":100,"ix":5}},{"ty":"tr","a":{"a":0,"k":[0,0],"ix":1},"s":{"a":0,"k":[100,100],"ix":3},"sk":{"a":0,"k":0,"ix":4},"p":{"a":0,"k":[160.807,54.259],"ix":2},"r":{"a":0,"k":0,"ix":6},"sa":{"a":0,"k":0,"ix":5},"o":{"a":0,"k":100,"ix":7}}]},{"ty":"gr","bm":0,"hd":false,"mn":"ADBE Vector Group","nm":"Grupo 2","ix":2,"cix":2,"np":2,"it":[{"ty":"sh","bm":0,"hd":false,"mn":"ADBE Vector Shape - Group","nm":"Trazado 1","ix":1,"d":1,"ks":{"a":0,"k":{"c":true,"i":[[-0.202,1.391],[1.39,0.201],[0.202,-1.391],[-1.39,-0.202]],"o":[[0.202,-1.391],[-1.391,-0.202],[-0.202,1.39],[1.391,0.202]],"v":[[2.518,0.365],[0.367,-2.518],[-2.518,-0.365],[-0.366,2.518]]},"ix":2}},{"ty":"fl","bm":0,"hd":false,"mn":"ADBE Vector Graphic - Fill","nm":"Relleno 1","c":{"a":0,"k":[1,1,1],"ix":4},"r":1,"o":{"a":0,"k":100,"ix":5}},{"ty":"tr","a":{"a":0,"k":[0,0],"ix":1},"s":{"a":0,"k":[100,100],"ix":3},"sk":{"a":0,"k":0,"ix":4},"p":{"a":0,"k":[164.333,29.981],"ix":2},"r":{"a":0,"k":0,"ix":6},"sa":{"a":0,"k":0,"ix":5},"o":{"a":0,"k":100,"ix":7}}]},{"ty":"gr","bm":0,"hd":false,"mn":"ADBE Vector Group","nm":"Grupo 3","ix":3,"cix":2,"np":2,"it":[{"ty":"sh","bm":0,"hd":false,"mn":"ADBE Vector Shape - Group","nm":"Trazado 1","ix":1,"d":1,"ks":{"a":0,"k":{"c":true,"i":[[-0.366,2.519],[2.518,0.366],[0.366,-2.518],[-2.517,-0.365]],"o":[[0.365,-2.518],[-2.519,-0.366],[-0.365,2.519],[2.519,0.366]],"v":[[4.56,0.663],[0.663,-4.56],[-4.56,-0.663],[-0.663,4.56]]},"ix":2}},{"ty":"fl","bm":0,"hd":false,"mn":"ADBE Vector Graphic - Fill","nm":"Relleno 1","c":{"a":0,"k":[1,1,1],"ix":4},"r":1,"o":{"a":0,"k":100,"ix":5}},{"ty":"tr","a":{"a":0,"k":[0,0],"ix":1},"s":{"a":0,"k":[100,100],"ix":3},"sk":{"a":0,"k":0,"ix":4},"p":{"a":0,"k":[162.57,42.119],"ix":2},"r":{"a":0,"k":0,"ix":6},"sa":{"a":0,"k":0,"ix":5},"o":{"a":0,"k":100,"ix":7}}]},{"ty":"gr","bm":0,"hd":false,"mn":"ADBE Vector Group","nm":"Grupo 4","ix":4,"cix":2,"np":2,"it":[{"ty":"sh","bm":0,"hd":false,"mn":"ADBE Vector Shape - Group","nm":"Trazado 1","ix":1,"d":1,"ks":{"a":0,"k":{"c":true,"i":[[0,0],[0,0],[0,0],[0,0]],"o":[[0,0],[0,0],[0,0],[0,0]],"v":[[8.486,21.378],[-14.216,18.081],[-8.485,-21.378],[14.217,-18.081]]},"ix":2}},{"ty":"st","bm":0,"hd":false,"mn":"ADBE Vector Graphic - Stroke","nm":"Trazo 1","lc":2,"lj":2,"ml":1,"o":{"a":0,"k":100,"ix":4},"w":{"a":0,"k":1.5,"ix":5},"c":{"a":0,"k":[0.1098,0.1569,0.2],"ix":3}},{"ty":"tr","a":{"a":0,"k":[0,0],"ix":1},"s":{"a":0,"k":[100,100],"ix":3},"sk":{"a":0,"k":0,"ix":4},"p":{"a":0,"k":[162.568,42.132],"ix":2},"r":{"a":0,"k":0,"ix":6},"sa":{"a":0,"k":0,"ix":5},"o":{"a":0,"k":100,"ix":7}}]},{"ty":"gr","bm":0,"hd":false,"mn":"ADBE Vector Group","nm":"Grupo 5","ix":5,"cix":2,"np":4,"it":[{"ty":"sh","bm":0,"hd":false,"mn":"ADBE Vector Shape - Group","nm":"Trazado 1","ix":1,"d":1,"ks":{"a":0,"k":{"c":true,"i":[[0,0],[0,0],[0,0],[0,0]],"o":[[0,0],[0,0],[0,0],[0,0]],"v":[[-8.485,-21.379],[-14.216,18.081],[8.486,21.379],[14.217,-18.081]]},"ix":2}},{"ty":"sh","bm":0,"hd":false,"mn":"ADBE Vector Shape - Group","nm":"Trazado 2","ix":2,"d":1,"ks":{"a":0,"k":{"c":true,"i":[[0,0],[0,0],[0,0],[0,0]],"o":[[0,0],[0,0],[0,0],[0,0]],"v":[[-6.503,-18.721],[11.56,-16.098],[6.502,18.721],[-11.559,16.099]]},"ix":2}},{"ty":"mm","bm":0,"hd":false,"mn":"ADBE Vector Filter - Merge","nm":"Combinar trazados 1","mm":1},{"ty":"fl","bm":0,"hd":false,"mn":"ADBE Vector Graphic - Fill","nm":"Relleno 1","c":{"a":0,"k":[1,1,1],"ix":4},"r":1,"o":{"a":0,"k":100,"ix":5}},{"ty":"tr","a":{"a":0,"k":[0,0],"ix":1},"s":{"a":0,"k":[100,100],"ix":3},"sk":{"a":0,"k":0,"ix":4},"p":{"a":0,"k":[162.568,42.132],"ix":2},"r":{"a":0,"k":0,"ix":6},"sa":{"a":0,"k":0,"ix":5},"o":{"a":0,"k":100,"ix":7}}]},{"ty":"gr","bm":0,"hd":false,"mn":"ADBE Vector Group","nm":"Grupo 6","ix":6,"cix":2,"np":2,"it":[{"ty":"sh","bm":0,"hd":false,"mn":"ADBE Vector Shape - Group","nm":"Trazado 1","ix":1,"d":1,"ks":{"a":0,"k":{"c":true,"i":[[0,0],[0,0],[0,0],[0,0]],"o":[[0,0],[0,0],[0,0],[0,0]],"v":[[-12.888,17.089],[-7.493,-20.05],[12.889,-17.09],[7.493,20.05]]},"ix":2}},{"ty":"fl","bm":0,"hd":false,"mn":"ADBE Vector Graphic - Fill","nm":"Relleno 1","c":{"a":0,"k":[0.1098,0.1569,0.2],"ix":4},"r":1,"o":{"a":0,"k":100,"ix":5}},{"ty":"tr","a":{"a":0,"k":[0,0],"ix":1},"s":{"a":0,"k":[100,100],"ix":3},"sk":{"a":0,"k":0,"ix":4},"p":{"a":0,"k":[162.569,42.132],"ix":2},"r":{"a":0,"k":0,"ix":6},"sa":{"a":0,"k":0,"ix":5},"o":{"a":0,"k":100,"ix":7}}]},{"ty":"gr","bm":0,"hd":false,"mn":"ADBE Vector Group","nm":"Grupo 7","ix":7,"cix":2,"np":2,"it":[{"ty":"sh","bm":0,"hd":false,"mn":"ADBE Vector Shape - Group","nm":"Trazado 1","ix":1,"d":1,"ks":{"a":0,"k":{"c":true,"i":[[0,1.405],[1.405,0],[0,-1.405],[-1.405,0]],"o":[[0,-1.405],[-1.405,0],[0,1.405],[1.405,0]],"v":[[2.544,0],[0,-2.544],[-2.544,0],[0,2.544]]},"ix":2}},{"ty":"fl","bm":0,"hd":false,"mn":"ADBE Vector Graphic - Fill","nm":"Relleno 1","c":{"a":0,"k":[1,1,1],"ix":4},"r":1,"o":{"a":0,"k":100,"ix":5}},{"ty":"tr","a":{"a":0,"k":[0,0],"ix":1},"s":{"a":0,"k":[100,100],"ix":3},"sk":{"a":0,"k":0,"ix":4},"p":{"a":0,"k":[154.685,54.385],"ix":2},"r":{"a":0,"k":0,"ix":6},"sa":{"a":0,"k":0,"ix":5},"o":{"a":0,"k":100,"ix":7}}]},{"ty":"gr","bm":0,"hd":false,"mn":"ADBE Vector Group","nm":"Grupo 8","ix":8,"cix":2,"np":2,"it":[{"ty":"sh","bm":0,"hd":false,"mn":"ADBE Vector Shape - Group","nm":"Trazado 1","ix":1,"d":1,"ks":{"a":0,"k":{"c":true,"i":[[0,1.405],[1.405,0],[0,-1.405],[-1.405,0]],"o":[[0,-1.405],[-1.405,0],[0,1.405],[1.405,0]],"v":[[2.544,0],[0,-2.544],[-2.544,0],[0,2.544]]},"ix":2}},{"ty":"fl","bm":0,"hd":false,"mn":"ADBE Vector Graphic - Fill","nm":"Relleno 1","c":{"a":0,"k":[1,1,1],"ix":4},"r":1,"o":{"a":0,"k":100,"ix":5}},{"ty":"tr","a":{"a":0,"k":[0,0],"ix":1},"s":{"a":0,"k":[100,100],"ix":3},"sk":{"a":0,"k":0,"ix":4},"p":{"a":0,"k":[154.685,29.854],"ix":2},"r":{"a":0,"k":0,"ix":6},"sa":{"a":0,"k":0,"ix":5},"o":{"a":0,"k":100,"ix":7}}]},{"ty":"gr","bm":0,"hd":false,"mn":"ADBE Vector Group","nm":"Grupo 9","ix":9,"cix":2,"np":2,"it":[{"ty":"sh","bm":0,"hd":false,"mn":"ADBE Vector Shape - Group","nm":"Trazado 1","ix":1,"d":1,"ks":{"a":0,"k":{"c":true,"i":[[0,2.545],[2.544,0],[0,-2.544],[-2.545,0]],"o":[[0,-2.544],[-2.545,0],[0,2.545],[2.544,0]],"v":[[4.607,-0.001],[0,-4.607],[-4.608,-0.001],[0,4.607]]},"ix":2}},{"ty":"fl","bm":0,"hd":false,"mn":"ADBE Vector Graphic - Fill","nm":"Relleno 1","c":{"a":0,"k":[1,1,1],"ix":4},"r":1,"o":{"a":0,"k":100,"ix":5}},{"ty":"tr","a":{"a":0,"k":[0,0],"ix":1},"s":{"a":0,"k":[100,100],"ix":3},"sk":{"a":0,"k":0,"ix":4},"p":{"a":0,"k":[154.685,42.12],"ix":2},"r":{"a":0,"k":0,"ix":6},"sa":{"a":0,"k":0,"ix":5},"o":{"a":0,"k":100,"ix":7}}]},{"ty":"gr","bm":0,"hd":false,"mn":"ADBE Vector Group","nm":"Grupo 10","ix":10,"cix":2,"np":2,"it":[{"ty":"sh","bm":0,"hd":false,"mn":"ADBE Vector Shape - Group","nm":"Trazado 1","ix":1,"d":1,"ks":{"a":0,"k":{"c":true,"i":[[0,0],[0,0],[0,0],[0,0]],"o":[[0,0],[0,0],[0,0],[0,0]],"v":[[11.47,19.937],[-11.47,19.937],[-11.47,-19.937],[11.47,-19.937]]},"ix":2}},{"ty":"st","bm":0,"hd":false,"mn":"ADBE Vector Graphic - Stroke","nm":"Trazo 1","lc":2,"lj":2,"ml":1,"o":{"a":0,"k":100,"ix":4},"w":{"a":0,"k":1.5,"ix":5},"c":{"a":0,"k":[0.1098,0.1569,0.2],"ix":3}},{"ty":"tr","a":{"a":0,"k":[0,0],"ix":1},"s":{"a":0,"k":[100,100],"ix":3},"sk":{"a":0,"k":0,"ix":4},"p":{"a":0,"k":[154.685,42.132],"ix":2},"r":{"a":0,"k":0,"ix":6},"sa":{"a":0,"k":0,"ix":5},"o":{"a":0,"k":100,"ix":7}}]},{"ty":"gr","bm":0,"hd":false,"mn":"ADBE Vector Group","nm":"Grupo 11","ix":11,"cix":2,"np":4,"it":[{"ty":"sh","bm":0,"hd":false,"mn":"ADBE Vector Shape - Group","nm":"Trazado 1","ix":1,"d":1,"ks":{"a":0,"k":{"c":true,"i":[[0,0],[0,0],[0,0],[0,0]],"o":[[0,0],[0,0],[0,0],[0,0]],"v":[[11.47,-19.937],[-11.47,-19.937],[-11.47,19.937],[11.47,19.937]]},"ix":2}},{"ty":"sh","bm":0,"hd":false,"mn":"ADBE Vector Shape - Group","nm":"Trazado 2","ix":2,"d":1,"ks":{"a":0,"k":{"c":true,"i":[[0,0],[0,0],[0,0],[0,0]],"o":[[0,0],[0,0],[0,0],[0,0]],"v":[[9.126,17.593],[-9.125,17.593],[-9.125,-17.592],[9.126,-17.592]]},"ix":2}},{"ty":"mm","bm":0,"hd":false,"mn":"ADBE Vector Filter - Merge","nm":"Combinar trazados 1","mm":1},{"ty":"fl","bm":0,"hd":false,"mn":"ADBE Vector Graphic - Fill","nm":"Relleno 1","c":{"a":0,"k":[1,1,1],"ix":4},"r":1,"o":{"a":0,"k":100,"ix":5}},{"ty":"tr","a":{"a":0,"k":[0,0],"ix":1},"s":{"a":0,"k":[100,100],"ix":3},"sk":{"a":0,"k":0,"ix":4},"p":{"a":0,"k":[154.685,42.132],"ix":2},"r":{"a":0,"k":0,"ix":6},"sa":{"a":0,"k":0,"ix":5},"o":{"a":0,"k":100,"ix":7}}]},{"ty":"gr","bm":0,"hd":false,"mn":"ADBE Vector Group","nm":"Grupo 12","ix":12,"cix":2,"np":2,"it":[{"ty":"sh","bm":0,"hd":false,"mn":"ADBE Vector Shape - Group","nm":"Trazado 1","ix":1,"d":1,"ks":{"a":0,"k":{"c":true,"i":[[0,0],[0,0],[0,0],[0,0]],"o":[[0,0],[0,0],[0,0],[0,0]],"v":[[-10.298,-18.764],[10.298,-18.764],[10.298,18.764],[-10.298,18.764]]},"ix":2}},{"ty":"fl","bm":0,"hd":false,"mn":"ADBE Vector Graphic - Fill","nm":"Relleno 1","c":{"a":0,"k":[0.1098,0.1569,0.2],"ix":4},"r":1,"o":{"a":0,"k":100,"ix":5}},{"ty":"tr","a":{"a":0,"k":[0,0],"ix":1},"s":{"a":0,"k":[100,100],"ix":3},"sk":{"a":0,"k":0,"ix":4},"p":{"a":0,"k":[154.685,42.132],"ix":2},"r":{"a":0,"k":0,"ix":6},"sa":{"a":0,"k":0,"ix":5},"o":{"a":0,"k":100,"ix":7}}]}],"ind":6},{"ty":4,"nm":"place contornos","sr":1,"st":0,"op":149,"ip":0,"hd":false,"ddd":0,"bm":0,"hasMask":false,"ao":0,"ks":{"a":{"a":0,"k":[160,139.25,0],"ix":1},"s":{"a":0,"k":[100,100,100],"ix":6},"sk":{"a":0,"k":0},"p":{"a":0,"k":[160,137,0],"ix":2},"r":{"a":1,"k":[{"o":{"x":0.333,"y":0},"i":{"x":0.667,"y":1},"s":[-103],"t":0},{"o":{"x":0.333,"y":0},"i":{"x":0.667,"y":1},"s":[7],"t":11},{"o":{"x":0.167,"y":0},"i":{"x":0.667,"y":1},"s":[0],"t":15},{"o":{"x":0.333,"y":0},"i":{"x":0.667,"y":1},"s":[0],"t":23},{"o":{"x":0.333,"y":0},"i":{"x":0.667,"y":1},"s":[-10],"t":27},{"s":[117],"t":37}],"ix":10},"sa":{"a":0,"k":0},"o":{"a":0,"k":100,"ix":11}},"ef":[],"shapes":[{"ty":"gr","bm":0,"hd":false,"mn":"ADBE Vector Group","nm":"Grupo 1","ix":1,"cix":2,"np":2,"it":[{"ty":"sh","bm":0,"hd":false,"mn":"ADBE Vector Shape - Group","nm":"Trazado 1","ix":1,"d":1,"ks":{"a":0,"k":{"c":true,"i":[[0,2.544],[2.544,0],[0,-2.545],[-2.545,0]],"o":[[0,-2.545],[-2.545,0],[0,2.544],[2.544,0]],"v":[[4.607,0.001],[0,-4.607],[-4.608,0.001],[0,4.607]]},"ix":2}},{"ty":"fl","bm":0,"hd":false,"mn":"ADBE Vector Graphic - Fill","nm":"Relleno 1","c":{"a":0,"k":[1,1,1],"ix":4},"r":1,"o":{"a":0,"k":100,"ix":5}},{"ty":"tr","a":{"a":0,"k":[0,0],"ix":1},"s":{"a":0,"k":[100,100],"ix":3},"sk":{"a":0,"k":0,"ix":4},"p":{"a":0,"k":[160,37.356],"ix":2},"r":{"a":0,"k":0,"ix":6},"sa":{"a":0,"k":0,"ix":5},"o":{"a":0,"k":100,"ix":7}}]},{"ty":"gr","bm":0,"hd":false,"mn":"ADBE Vector Group","nm":"Grupo 2","ix":2,"cix":2,"np":2,"it":[{"ty":"sh","bm":0,"hd":false,"mn":"ADBE Vector Shape - Group","nm":"Trazado 1","ix":1,"d":1,"ks":{"a":0,"k":{"c":true,"i":[[0,5.705],[8.374,0],[0,-8.374],[-4.486,-6.315],[-1.778,2.502]],"o":[[0,-8.374],[-8.374,0],[0,5.705],[1.778,2.502],[4.486,-6.315]],"v":[[15.162,-5.088],[0,-20.249],[-15.162,-5.088],[-3.639,17.747],[3.639,17.747]]},"ix":2}},{"ty":"st","bm":0,"hd":false,"mn":"ADBE Vector Graphic - Stroke","nm":"Trazo 1","lc":2,"lj":2,"ml":1,"o":{"a":0,"k":100,"ix":4},"w":{"a":0,"k":1.5,"ix":5},"c":{"a":0,"k":[0.1098,0.1569,0.2],"ix":3}},{"ty":"tr","a":{"a":0,"k":[0,0],"ix":1},"s":{"a":0,"k":[100,100],"ix":3},"sk":{"a":0,"k":0,"ix":4},"p":{"a":0,"k":[160,42.444],"ix":2},"r":{"a":0,"k":0,"ix":6},"sa":{"a":0,"k":0,"ix":5},"o":{"a":0,"k":100,"ix":7}}]},{"ty":"gr","bm":0,"hd":false,"mn":"ADBE Vector Group","nm":"Grupo 3","ix":3,"cix":2,"np":4,"it":[{"ty":"sh","bm":0,"hd":false,"mn":"ADBE Vector Shape - Group","nm":"Trazado 1","ix":1,"d":1,"ks":{"a":0,"k":{"c":true,"i":[[8.374,0],[0,-8.373],[-4.486,-6.316],[-1.375,0],[-0.889,1.251],[0,5.705]],"o":[[-8.374,0],[0,5.705],[0.889,1.251],[1.375,0],[4.486,-6.316],[0,-8.373]],"v":[[0,-19.937],[-15.162,-4.775],[-3.639,18.061],[0,19.937],[3.639,18.061],[15.162,-4.775]]},"ix":2}},{"ty":"sh","bm":0,"hd":false,"mn":"ADBE Vector Shape - Group","nm":"Trazado 2","ix":2,"d":1,"ks":{"a":0,"k":{"c":true,"i":[[-7.067,0],[0,-7.068],[7.047,-9.922],[0.696,0],[0.402,0.565],[0,3.728]],"o":[[7.067,0],[0,3.728],[-0.402,0.565],[-0.696,0],[-7.047,-9.922],[0,-7.068]],"v":[[0,-17.592],[12.817,-4.775],[1.728,16.703],[0,17.593],[-1.728,16.703],[-12.817,-4.775]]},"ix":2}},{"ty":"mm","bm":0,"hd":false,"mn":"ADBE Vector Filter - Merge","nm":"Combinar trazados 1","mm":1},{"ty":"fl","bm":0,"hd":false,"mn":"ADBE Vector Graphic - Fill","nm":"Relleno 1","c":{"a":0,"k":[1,1,1],"ix":4},"r":1,"o":{"a":0,"k":100,"ix":5}},{"ty":"tr","a":{"a":0,"k":[0,0],"ix":1},"s":{"a":0,"k":[100,100],"ix":3},"sk":{"a":0,"k":0,"ix":4},"p":{"a":0,"k":[160,42.132],"ix":2},"r":{"a":0,"k":0,"ix":6},"sa":{"a":0,"k":0,"ix":5},"o":{"a":0,"k":100,"ix":7}}]},{"ty":"gr","bm":0,"hd":false,"mn":"ADBE Vector Group","nm":"Grupo 4","ix":4,"cix":2,"np":2,"it":[{"ty":"sh","bm":0,"hd":false,"mn":"ADBE Vector Shape - Group","nm":"Trazado 1","ix":1,"d":1,"ks":{"a":0,"k":{"c":true,"i":[[1.081,0],[0.624,0.879],[0,3.965],[-7.714,0],[0,-7.713],[7.186,-10.115]],"o":[[-1.081,0],[-7.185,-10.116],[0,-7.713],[7.714,0],[0,3.966],[-0.624,0.879]],"v":[[0,18.764],[-2.684,17.382],[-13.99,-4.776],[0,-18.764],[13.99,-4.776],[2.683,17.382]]},"ix":2}},{"ty":"fl","bm":0,"hd":false,"mn":"ADBE Vector Graphic - Fill","nm":"Relleno 1","c":{"a":0,"k":[0.1098,0.1569,0.2],"ix":4},"r":1,"o":{"a":0,"k":100,"ix":5}},{"ty":"tr","a":{"a":0,"k":[0,0],"ix":1},"s":{"a":0,"k":[100,100],"ix":3},"sk":{"a":0,"k":0,"ix":4},"p":{"a":0,"k":[160,42.132],"ix":2},"r":{"a":0,"k":0,"ix":6},"sa":{"a":0,"k":0,"ix":5},"o":{"a":0,"k":100,"ix":7}}]}],"ind":7},{"ty":1,"nm":"Sólido Blanco 2","sr":1,"st":0,"op":110,"ip":0,"hd":false,"ddd":0,"bm":0,"hasMask":false,"ao":0,"ks":{"a":{"a":0,"k":[160,80,0],"ix":1},"s":{"a":0,"k":[100,100,100],"ix":6},"sk":{"a":0,"k":0},"p":{"a":0,"k":[160,80,0],"ix":2},"r":{"a":0,"k":0,"ix":10},"sa":{"a":0,"k":0},"o":{"a":0,"k":100,"ix":11}},"ef":[],"sc":"#ffffff","sh":160,"sw":320,"ind":8}],"v":"5.7.4","fr":25,"op":104,"ip":0,"assets":[]}